imagecast/__init__.py
imagecast/api.py
imagecast/cli.py
imagecast/core.py
imagecast/util.py
imagecast-0.7.0.dist-info/LICENSE
imagecast-0.7.0.dist-info/METADATA
imagecast-0.7.0.dist-info/WHEEL
imagecast-0.7.0.dist-info/entry_points.txt
imagecast-0.7.0.dist-info/top_level.txt
imagecast-0.7.0.dist-info/RECORD
