Metadata-Version: 2.1
Name: imagecast
Version: 0.7.0
Summary: Imagecast is like ImageMagick but for Pythonistas. Optionally provides its features via HTTP API.
Home-page: https://github.com/panodata/imagecast
Author: Andreas Motl
Author-email: andreas.motl@panodata.org
License: AGPL 3, EUPL 1.2
Keywords: image conversion http api proxy
Classifier: Programming Language :: Python
Classifier: Programming Language :: Python :: 3
Classifier: Programming Language :: Python :: 3.8
Classifier: Programming Language :: Python :: 3.9
Classifier: Programming Language :: Python :: 3.10
Classifier: Programming Language :: Python :: 3.11
Classifier: Programming Language :: Python :: 3.12
Classifier: Programming Language :: Python :: Implementation :: CPython
Classifier: License :: OSI Approved :: GNU Affero General Public License v3
Classifier: License :: OSI Approved :: European Union Public Licence 1.2 (EUPL 1.2)
Classifier: Development Status :: 4 - Beta
Classifier: Environment :: Console
Classifier: Environment :: Web Environment
Classifier: Intended Audience :: Developers
Classifier: Intended Audience :: Education
Classifier: Intended Audience :: Information Technology
Classifier: Intended Audience :: Manufacturing
Classifier: Intended Audience :: Science/Research
Classifier: Intended Audience :: System Administrators
Classifier: Intended Audience :: Telecommunications Industry
Classifier: Topic :: Communications
Classifier: Topic :: Internet
Classifier: Topic :: Internet :: WWW/HTTP
Classifier: Topic :: Scientific/Engineering :: Human Machine Interfaces
Classifier: Topic :: Scientific/Engineering :: Information Analysis
Classifier: Topic :: Scientific/Engineering :: Interface Engine/Protocol Translator
Classifier: Topic :: Software Development :: Embedded Systems
Classifier: Topic :: Software Development :: Libraries
Classifier: Topic :: System :: Archiving
Classifier: Topic :: Utilities
Classifier: Operating System :: POSIX
Classifier: Operating System :: Unix
Classifier: Operating System :: MacOS
License-File: LICENSE
Requires-Dist: docopt-ng <1,>=0.6
Requires-Dist: munch <5,>=2.3
Requires-Dist: Pillow <11,>=8
Requires-Dist: playwright <1.44
Requires-Dist: requests <3,>=2.23
Requires-Dist: requests-cache <2,>=0.5
Requires-Dist: typing-extensions <5 ; python_version < "3.9"
Provides-Extra: service
Requires-Dist: fastapi <0.111 ; extra == 'service'
Requires-Dist: pydantic-settings <3 ; extra == 'service'
Requires-Dist: uvicorn <0.30 ; extra == 'service'
